foursight_core/__init__.py
foursight_core/abstract_connection.py
foursight_core/app.py
foursight_core/app_utils.py
foursight_core/boto_s3.py
foursight_core/boto_sqs.py
foursight_core/buckets.py
foursight_core/captured_output.py
foursight_core/check_schema.py
foursight_core/check_setup.json
foursight_core/check_utils.py
foursight_core/checks/__init__.py
foursight_core/checks/access_key_expiration_detection.py
foursight_core/checks/codebuild_checks.py
foursight_core/checks/ecs_checks.py
foursight_core/checks/ecs_recovery_check.py
foursight_core/checks/helpers/__init__.py
foursight_core/checks/helpers/confchecks.py
foursight_core/checks/helpers/sys_utils.py
foursight_core/checks/helpers/wrangler_utils.py
foursight_core/checks/scaling_checks.py
foursight_core/checks/test_checks.py
foursight_core/decorators.py
foursight_core/deploy.py
foursight_core/environment.py
foursight_core/es_connection.py
foursight_core/exceptions.py
foursight_core/fs_connection.py
foursight_core/gitinfo.json
foursight_core/identity.py
foursight_core/mapping.json
foursight_core/package.py
foursight_core/react/api/auth.py
foursight_core/react/api/auth0_config.py
foursight_core/react/api/aws_ecs_services.py
foursight_core/react/api/aws_ecs_tasks.py
foursight_core/react/api/aws_ecs_types.py
foursight_core/react/api/aws_network.py
foursight_core/react/api/aws_s3.py
foursight_core/react/api/aws_stacks.py
foursight_core/react/api/checks.py
foursight_core/react/api/cognito.py
foursight_core/react/api/cookie_utils.py
foursight_core/react/api/datetime_utils.py
foursight_core/react/api/encoding_utils.py
foursight_core/react/api/encryption.py
foursight_core/react/api/envs.py
foursight_core/react/api/gac.py
foursight_core/react/api/ingestion_utils.py
foursight_core/react/api/jwt_utils.py
foursight_core/react/api/misc_utils.py
foursight_core/react/api/portal_access_key_utils.py
foursight_core/react/api/react_api.py
foursight_core/react/api/react_api_base.py
foursight_core/react/api/react_route_decorator.py
foursight_core-5.8.0.dist-info/LICENSE.txt
foursight_core-5.8.0.dist-info/METADATA
foursight_core-5.8.0.dist-info/WHEEL
foursight_core-5.8.0.dist-info/entry_points.txt
foursight_core-5.8.0.dist-info/RECORD
