Metadata-Version: 2.1
Name: foursight-core
Version: 5.8.0
Summary: Serverless Chalice Application for Monitoring
License: MIT
Author: 4DN-DCIC Team
Author-email: support@4dnucleome.org
Requires-Python: >=3.8.1,<3.13
Classifier: License :: OSI Approved :: MIT License
Classifier: Programming Language :: Python :: 3
Classifier: Programming Language :: Python :: 3.9
Classifier: Programming Language :: Python :: 3.10
Classifier: Programming Language :: Python :: 3.11
Classifier: Programming Language :: Python :: 3.12
Requires-Dist: Jinja2 (>=3.1.2,<4.0.0)
Requires-Dist: MarkupSafe (>=2.1.3,<3.0.0)
Requires-Dist: PyJWT (>=2.8.0,<3.0.0)
Requires-Dist: boto3 (>=1.34.136,<2.0.0)
Requires-Dist: botocore (>=1.34.136,<2.0.0)
Requires-Dist: click (>=7.1.2,<8.0.0)
Requires-Dist: cron-descriptor (>=1.2.31,<2.0.0)
Requires-Dist: cryptography (>=43.0.1,<44.0.0)
Requires-Dist: dcicutils (>=8.16.4,<9.0.0)
Requires-Dist: elasticsearch (==7.13.4)
Requires-Dist: elasticsearch-dsl (>=7.0.0,<8.0.0)
Requires-Dist: geocoder (==1.38.1)
Requires-Dist: gitpython (>=3.1.2,<4.0.0)
Requires-Dist: google (>=3.0.0,<4.0.0)
Requires-Dist: google-api-python-client (>=1.12.5,<2.0.0)
Requires-Dist: google-auth-oauthlib (>=0.7.0,<0.8.0)
Requires-Dist: pyDes (>=2.0.1,<3.0.0)
Requires-Dist: pytz (>=2020.1)
Requires-Dist: redis (>=4.5.1,<5.0.0)
Requires-Dist: toml (>=0.10.2,<1)
Requires-Dist: tzlocal (>=5.0.1,<6.0.0)
